eatlocal/__init__.py
eatlocal/__main__.py
eatlocal/console.py
eatlocal/constants.py
eatlocal/eatlocal.py
eatlocal-1.1.5.dist-info/METADATA
eatlocal-1.1.5.dist-info/WHEEL
eatlocal-1.1.5.dist-info/entry_points.txt
eatlocal-1.1.5.dist-info/licenses/LICENSE
eatlocal-1.1.5.dist-info/RECORD
