Metadata-Version: 2.3
Name: eatlocal
Version: 1.1.5
Summary: Tool to solve Pybites Platform exercices locally.
Project-URL: Source, https://github.com/PyBites-Open-Source/eatlocal
Requires-Python: >=3.12
Requires-Dist: beautifulsoup4>=4.12.3
Requires-Dist: install-playwright>=0.1.0
Requires-Dist: iterfzf>=1.4.0.54.3
Requires-Dist: pytest-playwright>=0.5.2
Requires-Dist: python-dotenv>=1.0.1
Requires-Dist: requests-cache>=1.2.1
Requires-Dist: requests>=2.32.3
Requires-Dist: rich>=13.9.2
Requires-Dist: typer>=0.12.5
Provides-Extra: dev
Requires-Dist: pre-commit>=4.0.1; extra == 'dev'
Requires-Dist: pytest-cov>=5.0.0; extra == 'dev'
Requires-Dist: pytest-coverage>=0.0; extra == 'dev'
Requires-Dist: pytest>=8.3.3; extra == 'dev'
